gym_CTgraph/CTgraph_conf.py
gym_CTgraph/CTgraph_env.py
gym_CTgraph/CTgraph_images.py
gym_CTgraph/CTgraph_plot.py
gym_CTgraph/__init__.py
gym_CTgraph-1.0.dist-info/LICENSE
gym_CTgraph-1.0.dist-info/METADATA
gym_CTgraph-1.0.dist-info/WHEEL
gym_CTgraph-1.0.dist-info/top_level.txt
gym_CTgraph-1.0.dist-info/RECORD
